LICENSE
README.md
pyproject.toml
setup.py
ezconfig/__init__.py
ezconfig/errors.py
ezconfig/ez_config.py
ezconfig/key_prompt.py
ezconfig/types.py
ezconfig/utils.py
python_ezconfig.egg-info/PKG-INFO
python_ezconfig.egg-info/SOURCES.txt
python_ezconfig.egg-info/dependency_links.txt
python_ezconfig.egg-info/requires.txt
python_ezconfig.egg-info/top_level.txt