Metadata-Version: 2.1
Name: python-ezconfig
Version: 0.2.0
Summary: Super easy access to configuration file, by pretty interface
Home-page: https://github.com/zrxmax/python-ezconfig
Author: zrxmax
Author-email: zrxmax@icloud.com
License: MIT
Keywords: ezconfig,python-ezconfig,easyconfig,easy,pretty,beatiful,beauti,config,env
Classifier: Development Status :: 3 - Alpha
Classifier: Programming Language :: Python :: 3
Classifier: License :: OSI Approved :: MIT License
Classifier: Operating System :: OS Independent
Requires-Python: >=3.7
License-File: LICENSE
